google/cloud/oracledatabase/__init__.py
google/cloud/oracledatabase/gapic_version.py
google/cloud/oracledatabase/py.typed
google/cloud/oracledatabase_v1/__init__.py
google/cloud/oracledatabase_v1/gapic_metadata.json
google/cloud/oracledatabase_v1/gapic_version.py
google/cloud/oracledatabase_v1/py.typed
google/cloud/oracledatabase_v1/services/__init__.py
google/cloud/oracledatabase_v1/services/oracle_database/__init__.py
google/cloud/oracledatabase_v1/services/oracle_database/async_client.py
google/cloud/oracledatabase_v1/services/oracle_database/client.py
google/cloud/oracledatabase_v1/services/oracle_database/pagers.py
google/cloud/oracledatabase_v1/services/oracle_database/transports/__init__.py
google/cloud/oracledatabase_v1/services/oracle_database/transports/base.py
google/cloud/oracledatabase_v1/services/oracle_database/transports/grpc.py
google/cloud/oracledatabase_v1/services/oracle_database/transports/grpc_asyncio.py
google/cloud/oracledatabase_v1/services/oracle_database/transports/rest.py
google/cloud/oracledatabase_v1/services/oracle_database/transports/rest_base.py
google/cloud/oracledatabase_v1/types/__init__.py
google/cloud/oracledatabase_v1/types/autonomous_database.py
google/cloud/oracledatabase_v1/types/autonomous_database_character_set.py
google/cloud/oracledatabase_v1/types/autonomous_db_backup.py
google/cloud/oracledatabase_v1/types/autonomous_db_version.py
google/cloud/oracledatabase_v1/types/common.py
google/cloud/oracledatabase_v1/types/database.py
google/cloud/oracledatabase_v1/types/database_character_set.py
google/cloud/oracledatabase_v1/types/db_node.py
google/cloud/oracledatabase_v1/types/db_server.py
google/cloud/oracledatabase_v1/types/db_system.py
google/cloud/oracledatabase_v1/types/db_system_initial_storage_size.py
google/cloud/oracledatabase_v1/types/db_system_shape.py
google/cloud/oracledatabase_v1/types/db_version.py
google/cloud/oracledatabase_v1/types/entitlement.py
google/cloud/oracledatabase_v1/types/exadata_infra.py
google_cloud_oracledatabase-0.4.0.dist-info/licenses/LICENSE
google_cloud_oracledatabase-0.4.0.dist-info/METADATA
google_cloud_oracledatabase-0.4.0.dist-info/WHEEL
google_cloud_oracledatabase-0.4.0.dist-info/top_level.txt
google_cloud_oracledatabase-0.4.0.dist-info/RECORD
